konseki/__init__.py
konseki/bin/konseki.py
konseki/modules/activity_display.py
konseki/modules/github_api.py
konseki-0.1.2.dist-info/LICENSE
konseki-0.1.2.dist-info/METADATA
konseki-0.1.2.dist-info/WHEEL
konseki-0.1.2.dist-info/entry_points.txt
konseki-0.1.2.dist-info/RECORD
