Metadata-Version: 2.3
Name: konseki
Version: 0.1.2
Summary: A Python CLI tool to view and summarize a GitHub user's recent activity from their public events.
License: Mozilla Public License Version 2.0
Author: Ahmad Azwar Annas
Author-email: ahmadazw2@gmail.com
Requires-Python: >=3.13
Classifier: License :: Other/Proprietary License
Classifier: Programming Language :: Python :: 3
Classifier: Programming Language :: Python :: 3.13
Requires-Dist: requests (>=2.32.3,<3.0.0)
Project-URL: Repository, https://github.com/Aerysh/konseki
